blecon_api/__init__.py
blecon_api/devices.py
blecon_api/main.py
blecon_api-0.1.1.dist-info/entry_points.txt
blecon_api-0.1.1.dist-info/WHEEL
blecon_api-0.1.1.dist-info/METADATA
blecon_api-0.1.1.dist-info/RECORD
