Metadata-Version: 2.1
Name: blecon-api
Version: 0.1.1
Summary: 
Author: danros
Author-email: dan.ros@blecon.net
Requires-Python: >=3.8,<4.0
Classifier: Programming Language :: Python :: 3
Classifier: Programming Language :: Python :: 3.10
Classifier: Programming Language :: Python :: 3.8
Classifier: Programming Language :: Python :: 3.9
Requires-Dist: requests[all] (>=2.27.1,<3.0.0)
Requires-Dist: typer[all] (>=0.4.1,<0.5.0)
